LambdaData.cpython-37m-darwin.so
LambdaDataTests/__init__.py
LambdaDataTests/speed_tests.py
LambdaDataTests/tests.py
LambdaData-0.1.16.dist-info/LICENSE
LambdaData-0.1.16.dist-info/METADATA
LambdaData-0.1.16.dist-info/WHEEL
LambdaData-0.1.16.dist-info/top_level.txt
LambdaData-0.1.16.dist-info/RECORD
