Metadata-Version: 2.1
Name: LambdaData
Version: 0.1.16
Summary: Data Science Iterator Algorithm Library
Home-page: UNKNOWN
Author: Robert Sharp
Author-email: webmaster@sharpdesigndigital.com
License: Free for non-commercial use
Keywords: Lambda School,Data Science Algorithm,accumulate,adjacent_difference,all_of,any_of,difference,exclusive_scan,fork,generate,generate_n,inclusive_scan,inner_product,intersection,iota,min_max,none_of,partial_sum,partition,product,reduce,star_sum,star_product,symmetric_difference,transform,transform_reduce,transposed_sums,union,zip_transform,matrix_multiplyvalue_span,star_cat_row,star_cat_col,random_range,shuffle,TruffleShuffle,StateLookup
Platform: Darwin
Platform: Linux
Classifier: Development Status :: 4 - Beta
Classifier: Programming Language :: Python :: 3.7
Classifier: Programming Language :: Cython
Classifier: Topic :: Software Development :: Libraries :: Python Modules
Requires-Python: >=3.6
Requires-Dist: pandas
Requires-Dist: MonkeyScope
